lazy_json_field/__init__.py
lazy_json_field/fields.py
lazy_json_field/lazy_json.py
lazy_json_field/tests/__init__.py
lazy_json_field/tests/test_encoder.py
lazy_json_field/tests/test_lazy_json.py
django_lazy_json-0.1.1.dist-info/LICENSE
django_lazy_json-0.1.1.dist-info/METADATA
django_lazy_json-0.1.1.dist-info/WHEEL
django_lazy_json-0.1.1.dist-info/RECORD
