Metadata-Version: 2.1
Name: django-lazy-json
Version: 0.1.1
Summary: Wrapper for Django's JSONField that allows for lazy loading of the JSON object.
Home-page: https://github.com/Krakenus/django_lazy_json_field
License: MIT
Author: Milan Vlasák
Author-email: krakenus02@gmail.com
Requires-Python: >=3.9,<4.0
Classifier: License :: OSI Approved :: MIT License
Classifier: Programming Language :: Python :: 3
Classifier: Programming Language :: Python :: 3.9
Classifier: Programming Language :: Python :: 3.10
Classifier: Programming Language :: Python :: 3.11
Classifier: Programming Language :: Python :: 3.12
Project-URL: Repository, https://github.com/Krakenus/django_lazy_json_field
